{
    "status": "ok",
    "totalResults": 10,
    "articles": [
        {
            "source": {
                "id": null,
                "name": "Yahoo Entertainment"
            },
            "author": "Simply Wall St",
            "title": "iRhythm Technologies, Inc. (NASDAQ:IRTC) Shares Could Be 33% Below Their Intrinsic Value Estimate",
            "description": "Key Insights Using the 2 Stage Free Cash Flow to Equity, iRhythm Technologies fair value estimate is US$141 iRhythm...",
            "url": "https://finance.yahoo.com/news/irhythm-technologies-inc-nasdaq-irtc-174231186.html",
            "urlToImage": "https://media.zenfs.com/en/simply_wall_st__316/983f2bdfe32b19227b1d118c45bf4f09",
            "publishedAt": "2023-09-20T17:42:31Z",
            "content": "Key Insights\r\n<ul><li>Using the 2 Stage Free Cash Flow to Equity, iRhythm Technologies fair value estimate is US$141\r\n</li><li>iRhythm Technologies' US$93.51 share price signals that it might be 33% \u2026 [+7822 chars]"
        },
        {
            "source": {
                "id": null,
                "name": "Yahoo Entertainment"
            },
            "author": "GuruFocus Research",
            "title": "Unveiling iRhythm Technologies (IRTC)'s Value: Is It Really Priced Right? A Comprehensive Guide",
            "description": "An in-depth analysis of iRhythm Technologies' intrinsic value and financial performance",
            "url": "https://finance.yahoo.com/news/unveiling-irhythm-technologies-irtc-value-154742346.html",
            "urlToImage": "https://media.zenfs.com/en/us.finance.gurufocus/502a39b74979a5cee8b14bd37f76d9d2",
            "publishedAt": "2023-09-22T15:47:42Z",
            "content": "The stock of iRhythm Technologies Inc (NASDAQ:IRTC) has experienced a daily loss of -1.95% and a 3-month loss of -13.05%. With a Loss Per Share of 3.28, the question arises: is the stock significantl\u2026 [+5749 chars]"
        },
        {
            "source": {
                "id": null,
                "name": "Yahoo Entertainment"
            },
            "author": "GuruFocus Research",
            "title": "Unveiling iRhythm Technologies (IRTC)'s Value: Is It Really Priced Right? A Comprehensive Guide",
            "description": "An in-depth analysis of iRhythm Technologies' intrinsic value based on its financial performance and market trends.",
            "url": "https://finance.yahoo.com/news/unveiling-irhythm-technologies-irtc-value-233552619.html",
            "urlToImage": "https://media.zenfs.com/en/us.finance.gurufocus/502a39b74979a5cee8b14bd37f76d9d2",
            "publishedAt": "2023-09-27T23:35:52Z",
            "content": "iRhythm Technologies Inc (NASDAQ:IRTC) has seen a daily gain of 7.4%, but has experienced a 3-month loss of -5.76%. With an Earnings Per Share (EPS) loss of 3.28, the question arises: is the stock si\u2026 [+5597 chars]"
        },
        {
            "source": {
                "id": null,
                "name": "Marketscreener.com"
            },
            "author": "GlobeNewswire",
            "title": "IRhythm Launches Next Generation Zio Monitor and Enhanced Zio Service: Its Smallest, Lightest and Thinnest Cardiac Monitor",
            "description": "(marketscreener.com) iRhythm is launching its next generation long-term ambulatory cardiac monitor in the U.S.Zio\u00ae monitor builds on the high performance of Zio\u00ae XT that, together with its enhanced Zio\u00ae long term continuous cardiac monitoring service, provide\u2026",
            "url": "https://www.marketscreener.com/quote/stock/IRHYTHM-TECHNOLOGIES-INC-31670646/news/IRhythm-Launches-Next-Generation-Zio-Monitor-and-Enhanced-Zio-Service-Its-Smallest-Lightest-and-Th-44922308/",
            "urlToImage": "https://www.marketscreener.com/images/twitter_MS_fdnoir.png",
            "publishedAt": "2023-09-26T12:06:02Z",
            "content": "<ul><li>iRhythm is launching its next generation long-term ambulatory cardiac monitor in the U.S.</li><li>Zio\u00ae monitor builds on the high performance of Zio\u00ae XT that, together with its enhanced Zio\u00ae \u2026 [+6851 chars]"
        },
        {
            "source": {
                "id": null,
                "name": "Marketscreener.com"
            },
            "author": "Business Wire",
            "title": "HeartBeam Appoints Richa Gujarati and Pooja Chatterjee to Senior Management Team",
            "description": "(marketscreener.com) \nExperienced Leaders to Support Clinical Development and Commercialization of HeartBeam\u2019s Ambulatory VECG Products\n\nhttps://www.marketscreener.com/quote/stock/HEARTBEAM-INC-128130723/news/HeartBeam-Appoints-Richa-Gujarati-and-Pooja-Chatte\u2026",
            "url": "https://www.marketscreener.com/quote/stock/HEARTBEAM-INC-128130723/news/HeartBeam-Appoints-Richa-Gujarati-and-Pooja-Chatterjee-to-Senior-Management-Team-44922563/",
            "urlToImage": "https://www.marketscreener.com/images/twitter_MS_fdnoir.png",
            "publishedAt": "2023-09-26T12:35:02Z",
            "content": "Experienced Leaders to Support Clinical Development and Commercialization of HeartBeams Ambulatory VECG Products\r\nHeartBeam, Inc. (NASDAQ: BEAT), a cardiac technology company that has developed the f\u2026 [+5790 chars]"
        },
        {
            "source": {
                "id": null,
                "name": "GlobeNewswire"
            },
            "author": "MarketsandMarkets Research Pvt. Ltd.",
            "title": "Wearable Healthcare Devices Market is Expected to Reach $30.1 billion | MarketsandMarkets.",
            "description": "Chicago, Oct. 11, 2023 (GLOBE NEWSWIRE) -- The wearable healthcare devices industry is poised for remarkable growth in the near future. As technological advancements continue to reshape the healthcare landscape, these innovative gadgets are set to play an inc\u2026",
            "url": "https://www.globenewswire.com/news-release/2023/10/11/2758349/0/en/Wearable-Healthcare-Devices-Market-is-Expected-to-Reach-30-1-billion-MarketsandMarkets.html",
            "urlToImage": "https://ml.globenewswire.com/Resource/Download/afcc5182-4ae0-43a8-a965-4351d590b7ed",
            "publishedAt": "2023-10-11T12:30:00Z",
            "content": "Chicago, Oct. 11, 2023 (GLOBE NEWSWIRE) -- The wearable healthcare devices industry is poised for remarkable growth in the near future. As technological advancements continue to reshape the healthcar\u2026 [+13439 chars]"
        },
        {
            "source": {
                "id": null,
                "name": "PR Newswire UK"
            },
            "author": null,
            "title": "Holter Monitor Market to Reach $1.20 Billion by 2029, 3-Channel Type Monitors Expected to Make the Most Substantial Contribution to Market Share - Arizton",
            "description": "CHICAGO, Oct. 10, 2023 /PRNewswire/ -- According to Arizton's latest research report, the holter monitor market growing at a CAGR of 8.45% during 2023-2029. The report analyses the current state of the global Holter monitor market and its market dynamics from\u2026",
            "url": "https://www.prnewswire.co.uk/news-releases/holter-monitor-market-to-reach-1-20-billion-by-2029--3-channel-type-monitors-expected-to-make-the-most-substantial-contribution-to-market-share---arizton-301952179.html",
            "urlToImage": "https://mma.prnewswire.com/media/2243068/HOLTER_MONITOR_MARKET_1.jpg?p=facebook",
            "publishedAt": "2023-10-10T18:50:00Z",
            "content": "CHICAGO, Oct. 10, 2023 /PRNewswire/ -- According to Arizton's latest research report, the holter monitor market\r\n growing at a CAGR of 8.45% during 2023-2029.\r\nThe report analyses the current state o\u2026 [+9221 chars]"
        },
        {
            "source": {
                "id": null,
                "name": "GlobeNewswire"
            },
            "author": "HMG Strategy",
            "title": "CIO Leadership: Leading as the CEO of Technology Will Drive the Discussion at the 2023 Minneapolis CIO Executive Leadership Summit on November 2",
            "description": "Coming Soon: the 2023 Silicon Valley CIO Executive Leadership Summit Coming Soon: the 2023 Silicon Valley CIO Executive Leadership Summit",
            "url": "https://www.globenewswire.com/news-release/2023/10/05/2755705/0/en/CIO-Leadership-Leading-as-the-CEO-of-Technology-Will-Drive-the-Discussion-at-the-2023-Minneapolis-CIO-Executive-Leadership-Summit-on-November-2.html",
            "urlToImage": "https://ml.globenewswire.com/Resource/Download/6e05ac8d-d2e7-492c-ad71-0e262d490e75",
            "publishedAt": "2023-10-05T17:07:00Z",
            "content": "WESTPORT, Conn., Oct. 05, 2023 (GLOBE NEWSWIRE) -- HMG Strategy, the Worlds #1 platform for enabling technology executives to reimagine the enterprise and reshape the business world, is excited to an\u2026 [+12120 chars]"
        },
        {
            "source": {
                "id": null,
                "name": "PRNewswire"
            },
            "author": null,
            "title": "Weight-loss Programs Level Up With Smart Wearable Devices",
            "description": "FinancialBuzz.com News Commentary NEW YORK, Sept. 15, 2023 /PRNewswire/ -- The wearable technology market has evolved in recent years into a major tech segment, in large part thanks to consumer market growth which is driven by sales of smartwatches. Major com\u2026",
            "url": "https://www.prnewswire.com/news-releases/weight-loss-programs-level-up-with-smart-wearable-devices-301928589.html",
            "urlToImage": null,
            "publishedAt": "2023-09-15T13:00:00Z",
            "content": "FinancialBuzz.com News Commentary\r\nNEW YORK, Sept. 15, 2023 /PRNewswire/ -- The wearable technology market has evolved in recent years into a major tech segment, in large part thanks to consumer mark\u2026 [+14891 chars]"
        },
        {
            "source": {
                "id": null,
                "name": "PRNewswire"
            },
            "author": null,
            "title": "Sensor Patch Market to Reach $56.37 Billion, Globally, by 2032 at 43.2% CAGR: Allied Market Research",
            "description": "The global sensor patch market is driven by factors such as usage of sensor patches in sports industry and the surge in per capita income in healthcare industry. PORTLAND, Ore., Oct. 4, 2023 /PRNewswire/ -- Allied Market Research published a report, titled, \"\u2026",
            "url": "https://www.prnewswire.com/news-releases/sensor-patch-market-to-reach-56-37-billion-globally-by-2032-at-43-2-cagr-allied-market-research-301946813.html",
            "urlToImage": "https://mma.prnewswire.com/media/636519/Allied_Market_Research_Logo.jpg?p=facebook",
            "publishedAt": "2023-10-04T08:23:00Z",
            "content": "The global sensor patch market is driven by factors such as usage of sensor patches in sports industry and the surge in per capita income in healthcare industry.\r\nPORTLAND, Ore., Oct. 4, 2023 /PRNews\u2026 [+11390 chars]"
        }
    ]
}