{
    "status": "ok",
    "totalResults": 2,
    "articles": [
        {
            "source": {
                "id": null,
                "name": "Yahoo Entertainment"
            },
            "author": "GuruFocus Research",
            "title": "CFO Mitch Hill Sells 6,500 Shares of Inari Medical Inc",
            "description": "On September 12, 2023, Mitch Hill, the Chief Financial Officer of Inari Medical Inc (NASDAQ:NARI), sold 6,500 shares of the company.",
            "url": "https://finance.yahoo.com/news/cfo-mitch-hill-sells-6-230308239.html",
            "urlToImage": "https://media.zenfs.com/en/us.finance.gurufocus/a95bc9bca3baf9a4bdcd7da610fa0423",
            "publishedAt": "2023-09-14T23:03:08Z",
            "content": "On September 12, 2023, Mitch Hill, the Chief Financial Officer of Inari Medical Inc (NASDAQ:NARI), sold 6,500 shares of the company. This move is part of a broader trend of insider selling at Inari M\u2026 [+2300 chars]"
        },
        {
            "source": {
                "id": null,
                "name": "GlobeNewswire"
            },
            "author": "The Insight Partners",
            "title": "Thrombectomy Devices Market worth $2.1 Billion by 2027 - Exclusive Report by The Insight Partners",
            "description": "Global thrombectomy devices market is growing at a CAGR of 5.9% from 2019 to 2027. Global thrombectomy devices market is growing at a CAGR of 5.9% from 2019 to 2027.",
            "url": "https://www.globenewswire.com/news-release/2023/09/20/2746549/0/en/Thrombectomy-Devices-Market-worth-2-1-Billion-by-2027-Exclusive-Report-by-The-Insight-Partners.html",
            "urlToImage": "https://ml.globenewswire.com/Resource/Download/efd8c9da-ac10-487a-a083-ec8f33cad35e",
            "publishedAt": "2023-09-20T13:09:00Z",
            "content": "Pune, India., Sept. 20, 2023 (GLOBE NEWSWIRE) -- The thrombectomy devices market growth is propelled by elevating incidences of CVDs and neurological diseases, technological advancements, government \u2026 [+7417 chars]"
        }
    ]
}