{
    "status": "ok",
    "totalResults": 5,
    "articles": [
        {
            "source": {
                "id": null,
                "name": "ETF Daily News"
            },
            "author": "MarketBeat News",
            "title": "LeMaitre Vascular, Inc. (NASDAQ:LMAT) Plans Quarterly Dividend of $0.14",
            "description": "LeMaitre Vascular, Inc. (NASDAQ:LMAT \u2013 Get Free Report) declared a quarterly dividend on Tuesday, October 24th, NASDAQ reports. Stockholders of record on Thursday, November 16th will be given a dividend of 0.14 per share by the medical instruments supplier on\u2026",
            "url": "https://www.etfdailynews.com/2023/11/13/lemaitre-vascular-inc-nasdaqlmat-plans-quarterly-dividend-of-0-14/",
            "urlToImage": "https://www.americanbankingnews.com/wp-content/timthumb/timthumb.php?src=https://www.marketbeat.com/logos/lemaitre-vascular-inc-logo.jpg?v=20221205140046&w=240&h=240&zc=2",
            "publishedAt": "2023-11-13T15:10:51Z",
            "content": "LeMaitre Vascular, Inc. (NASDAQ:LMAT \u2013 Get Free Report) declared a quarterly dividend on Tuesday, October 24th, NASDAQ reports. Stockholders of record on Thursday, November 16th will be given a divid\u2026 [+5601 chars]"
        },
        {
            "source": {
                "id": null,
                "name": "ETF Daily News"
            },
            "author": "MarketBeat News",
            "title": "Crawford Investment Counsel Inc. Sells 1,905 Shares of LeMaitre Vascular, Inc. (NASDAQ:LMAT)",
            "description": "Crawford Investment Counsel Inc. trimmed its holdings in shares of LeMaitre Vascular, Inc. (NASDAQ:LMAT \u2013 Free Report) by 1.7% during the second quarter, according to its most recent 13F filing with the Securities and Exchange Commission (SEC). The fund owned\u2026",
            "url": "https://www.etfdailynews.com/2023/12/02/crawford-investment-counsel-inc-sells-1905-shares-of-lemaitre-vascular-inc-nasdaqlmat/",
            "urlToImage": "https://www.americanbankingnews.com/wp-content/timthumb/timthumb.php?src=https://www.marketbeat.com/logos/lemaitre-vascular-inc-logo.jpg?v=20221205140046&w=240&h=240&zc=2",
            "publishedAt": "2023-12-02T16:36:54Z",
            "content": "Crawford Investment Counsel Inc. trimmed its holdings in shares of LeMaitre Vascular, Inc. (NASDAQ:LMAT \u2013 Free Report) by 1.7% during the second quarter, according to its most recent 13F filing with \u2026 [+5600 chars]"
        },
        {
            "source": {
                "id": null,
                "name": "ETF Daily News"
            },
            "author": "MarketBeat News",
            "title": "LeMaitre Vascular, Inc. (NASDAQ:LMAT) Shares Sold by Bridge City Capital LLC",
            "description": "Bridge City Capital LLC cut its holdings in shares of LeMaitre Vascular, Inc. (NASDAQ:LMAT \u2013 Free Report) by 21.8% in the second quarter, according to its most recent filing with the Securities and Exchange Commission. The firm owned 57,111 shares of the medi\u2026",
            "url": "https://www.etfdailynews.com/2023/11/19/lemaitre-vascular-inc-nasdaqlmat-shares-sold-by-bridge-city-capital-llc/",
            "urlToImage": "https://www.americanbankingnews.com/wp-content/timthumb/timthumb.php?src=https://www.marketbeat.com/logos/lemaitre-vascular-inc-logo.jpg?v=20221205140046&w=240&h=240&zc=2",
            "publishedAt": "2023-11-19T17:34:41Z",
            "content": "Bridge City Capital LLC cut its holdings in shares of LeMaitre Vascular, Inc. (NASDAQ:LMAT \u2013 Free Report) by 21.8% in the second quarter, according to its most recent filing with the Securities and E\u2026 [+5888 chars]"
        },
        {
            "source": {
                "id": null,
                "name": "ETF Daily News"
            },
            "author": "MarketBeat News",
            "title": "Summit Creek Advisors LLC Sells 96,838 Shares of LeMaitre Vascular, Inc. (NASDAQ:LMAT)",
            "description": "Summit Creek Advisors LLC lessened its holdings in shares of LeMaitre Vascular, Inc. (NASDAQ:LMAT \u2013 Free Report) by 40.7% during the 2nd quarter, according to its most recent disclosure with the SEC. The fund owned 141,202 shares of the medical instruments su\u2026",
            "url": "https://www.etfdailynews.com/2023/11/12/summit-creek-advisors-llc-sells-96838-shares-of-lemaitre-vascular-inc-nasdaqlmat/",
            "urlToImage": "https://www.americanbankingnews.com/wp-content/timthumb/timthumb.php?src=https://www.marketbeat.com/logos/lemaitre-vascular-inc-logo.jpg?v=20221205140046&w=240&h=240&zc=2",
            "publishedAt": "2023-11-12T15:02:44Z",
            "content": "Summit Creek Advisors LLC lessened its holdings in shares of LeMaitre Vascular, Inc. (NASDAQ:LMAT \u2013 Free Report) by 40.7% during the 2nd quarter, according to its most recent disclosure with the SEC.\u2026 [+5129 chars]"
        },
        {
            "source": {
                "id": null,
                "name": "GlobeNewswire"
            },
            "author": "SPHERICAL INSIGHTS LLP",
            "title": "Global Vascular Patches Market Size to Grow USD 626 Million by 2032 | CAGR of 5.9%",
            "description": "The Global Vascular Patches Market Size was valued at USD 353 Million in 2022 and the Worldwide Vascular Patches Market size is expected to reach USD 626 Million by 2032, according to a research report published by Spherical Insights & Consulting. Companies C\u2026",
            "url": "https://www.globenewswire.com/news-release/2023/11/28/2786732/0/en/Global-Vascular-Patches-Market-Size-to-Grow-USD-626-Million-by-2032-CAGR-of-5-9.html",
            "urlToImage": "https://ml.globenewswire.com/Resource/Download/b27a94e8-407e-46ae-a5c2-47bb2a1c8a2e",
            "publishedAt": "2023-11-28T10:30:00Z",
            "content": "New York, United States, Nov. 28, 2023 (GLOBE NEWSWIRE) -- The Global Vascular Patches Market Size is to Grow from USD 353 Million in 2022 to USD 626 Million by 2032, at a Compound Annual Growth Rate\u2026 [+11644 chars]"
        }
    ]
}